fabricatio/__init__.py
fabricatio/actions/__init__.py
fabricatio/capabilities/__init__.py
fabricatio/models/__init__.py
fabricatio/py.typed
fabricatio/rust.cpython-313-aarch64-linux-gnu.so
fabricatio/workflows/__init__.py
fabricatio-0.24.2.data/scripts/tdown
fabricatio-0.24.2.dist-info/METADATA
fabricatio-0.24.2.dist-info/WHEEL
fabricatio-0.24.2.dist-info/licenses/LICENSE
fabricatio-0.24.2.dist-info/RECORD
