Metadata-Version: 2.4
Name: fabricatio
Version: 0.24.2
Classifier: License :: OSI Approved :: MIT License
Classifier: Programming Language :: Rust
Classifier: Programming Language :: Python :: 3.12
Classifier: Programming Language :: Python :: 3.13
Classifier: Programming Language :: Python :: 3.14
Classifier: Programming Language :: Python :: Implementation :: CPython
Classifier: Framework :: AsyncIO
Classifier: Framework :: Pydantic :: 2
Classifier: Typing :: Typed
Requires-Dist: fabricatio-core
Requires-Dist: fabricatio-actions ; extra == 'actions'
Requires-Dist: fabricatio-agent ; extra == 'agent'
Requires-Dist: fabricatio-anki ; extra == 'anki'
Requires-Dist: fabricatio-capabilities ; extra == 'capabilities'
Requires-Dist: fabricatio-capable ; extra == 'capable'
Requires-Dist: fabricatio-character ; extra == 'character'
Requires-Dist: fabricatio-checkpoint ; extra == 'checkpoint'
Requires-Dist: fabricatio-diff ; extra == 'diff'
Requires-Dist: fabricatio-digest ; extra == 'digest'
Requires-Dist: fabricatio[rag,typst,rule,judge,capabilities,actions,improve,digest,memory,anki,question,tagging,yue,tool,plot,translate,locale,diff,thinking,agent,team,capable,novel,character,checkpoint,webui] ; extra == 'full'
Requires-Dist: fabricatio-improve ; extra == 'improve'
Requires-Dist: fabricatio-judge ; extra == 'judge'
Requires-Dist: fabricatio-locale ; extra == 'locale'
Requires-Dist: fabricatio-memory ; extra == 'memory'
Requires-Dist: fabricatio-novel ; extra == 'novel'
Requires-Dist: fabricatio-plot ; extra == 'plot'
Requires-Dist: fabricatio-question ; extra == 'question'
Requires-Dist: fabricatio-rag ; extra == 'rag'
Requires-Dist: fabricatio-rule ; extra == 'rule'
Requires-Dist: fabricatio-tagging ; extra == 'tagging'
Requires-Dist: fabricatio-team ; extra == 'team'
Requires-Dist: fabricatio-thinking ; extra == 'thinking'
Requires-Dist: fabricatio-tool ; extra == 'tool'
Requires-Dist: fabricatio-translate ; extra == 'translate'
Requires-Dist: fabricatio-typst ; extra == 'typst'
Requires-Dist: fabricatio-webui ; extra == 'webui'
Requires-Dist: fabricatio-yue ; extra == 'yue'
Provides-Extra: actions
Provides-Extra: agent
Provides-Extra: anki
Provides-Extra: capabilities
Provides-Extra: capable
Provides-Extra: character
Provides-Extra: checkpoint
Provides-Extra: diff
Provides-Extra: digest
Provides-Extra: full
Provides-Extra: improve
Provides-Extra: judge
Provides-Extra: locale
Provides-Extra: memory
Provides-Extra: novel
Provides-Extra: plot
Provides-Extra: question
Provides-Extra: rag
Provides-Extra: rule
Provides-Extra: tagging
Provides-Extra: team
Provides-Extra: thinking
Provides-Extra: tool
Provides-Extra: translate
Provides-Extra: typst
Provides-Extra: webui
Provides-Extra: yue
License-File: LICENSE
Summary: A LLM multi-agent framework.
Keywords: ai,agents,multi-agent,llm,pyo3
Author-email: Whth <zettainspector@foxmail.com>
Requires-Python: >=3.12, <3.15
Project-URL: Homepage, https://github.com/Whth/fabricatio
Project-URL: Issues, https://github.com/Whth/fabricatio/issues
Project-URL: Repository, https://github.com/Whth/fabricatio
